pdfrename/__init__.py
pdfrename/pdfrename.py
pdfrename-0.1.dist-info/DESCRIPTION.rst
pdfrename-0.1.dist-info/METADATA
pdfrename-0.1.dist-info/RECORD
pdfrename-0.1.dist-info/WHEEL
pdfrename-0.1.dist-info/entry_points.txt
pdfrename-0.1.dist-info/metadata.json
pdfrename-0.1.dist-info/top_level.txt
