Metadata-Version: 2.0
Name: pdfrename
Version: 0.1
Summary: A tool for renaming a batch of pdf files
Home-page: https://github.com/xoolive/pdfrename
Author: Xavier Olive
Author-email: xo.olive@gmail.com
License: MIT
Platform: UNKNOWN
Requires-Dist: pdfminer
